ml-lab/__init__.py
ml-lab/prog1.py
ml-lab/prog10.py
ml-lab/prog2.py
ml-lab/prog3.py
ml-lab/prog4.py
ml-lab/prog5.py
ml-lab/prog6.py
ml-lab/prog7.py
ml-lab/prog8.py
ml-lab/prog9.py
mllab/__init__.py
mllab/prog1.py
mllab/prog10.py
mllab/prog2.py
mllab/prog3.py
mllab/prog4.py
mllab/prog5.py
mllab/prog6.py
mllab/prog7.py
mllab/prog8.py
mllab/prog9.py
mluvce-0.1.0.dist-info/METADATA
mluvce-0.1.0.dist-info/WHEEL
mluvce-0.1.0.dist-info/top_level.txt
mluvce-0.1.0.dist-info/RECORD
