Metadata-Version: 2.1
Name: mluvce
Version: 0.1.0
Summary: ML-UVCE Python Package
Author: Anonymous
